core_ai_evaluation/__init__.py
core_ai_evaluation/main.py
core_ai_evaluation/api/__init__.py
core_ai_evaluation/api/answer_generator.py
core_ai_evaluation/api/models.py
core_ai_evaluation/api/router.py
core_ai_evaluation/configuration/__init__.py
core_ai_evaluation/configuration/azure.py
core_ai_evaluation/configuration/gemini.py
core_ai_evaluation/configuration/ollama.py
core_ai_evaluation/configuration/provider.py
core_ai_evaluation/configuration/utils.py
core_ai_evaluation/configuration/vertex_ai_anthropic.py
core_ai_evaluation/evaluation/__init__.py
core_ai_evaluation/evaluation/dataset_loader.py
core_ai_evaluation/evaluation/evaluation_model.py
core_ai_evaluation/evaluation/evaluator.py
core_ai_evaluation/evaluation/models.py
core_ai_evaluation/evaluation/service.py
core_ai_evaluation/evaluation/utils.py
core_ai_evaluation/shared/__init__.py
core_ai_evaluation/shared/log.py
core_ai_evaluation/shared/setup_helper.py
core_ai_evaluation/shared/utils.py
core_ai_evaluation-1.0.11.dist-info/METADATA
core_ai_evaluation-1.0.11.dist-info/WHEEL
core_ai_evaluation-1.0.11.dist-info/licenses/LICENSE
core_ai_evaluation-1.0.11.dist-info/RECORD
