Metadata-Version: 2.4
Name: core-ai-evaluation
Version: 1.0.11
Summary: Evaluation framework for CoreAI.
License-File: LICENSE
Requires-Python: >=3.11
Requires-Dist: anthropic>=0.42.0
Requires-Dist: azure-storage-blob>=12.25.1
Requires-Dist: bert-score>=0.3.13
Requires-Dist: datasets>=3.4.1
Requires-Dist: debugpy>=1.8.13
Requires-Dist: deepeval>=2.6.5
Requires-Dist: fastapi>=0.115.12
Requires-Dist: gcsfs>=2024.12.0
Requires-Dist: google-cloud-storage>=2.18.2
Requires-Dist: langchain-google-vertexai>=2.0.10
Requires-Dist: langchain-ollama>=0.2.1
Requires-Dist: langchain-openai>=0.3.12
Requires-Dist: numpy<2.0.0
Requires-Dist: pydantic-core>=2.23.4
Requires-Dist: pydantic>=2.9.2
Requires-Dist: python-dotenv>=1.0.1
Requires-Dist: structlog>=24.4.0
Requires-Dist: toml>=0.10.2
Requires-Dist: torch==2.2.1
Requires-Dist: uvicorn[standard]>=0.34.2
